careamics/__init__.py
careamics/careamist.py
careamics/conftest.py
careamics/nm_training_placeholder.py
careamics/py.typed
careamics/cli/__init__.py
careamics/cli/conf.py
careamics/cli/main.py
careamics/cli/utils.py
careamics/config/__init__.py
careamics/config/configuration.py
careamics/config/configuration_factories.py
careamics/config/algorithms/__init__.py
careamics/config/algorithms/care_algorithm_config.py
careamics/config/algorithms/hdn_algorithm_config.py
careamics/config/algorithms/microsplit_algorithm_config.py
careamics/config/algorithms/n2n_algorithm_config.py
careamics/config/algorithms/n2v_algorithm_config.py
careamics/config/algorithms/pn2v_algorithm_config.py
careamics/config/algorithms/unet_algorithm_config.py
careamics/config/algorithms/vae_algorithm_config.py
careamics/config/architectures/__init__.py
careamics/config/architectures/architecture_config.py
careamics/config/architectures/lvae_config.py
careamics/config/architectures/unet_config.py
careamics/config/data/__init__.py
careamics/config/data/data_config.py
careamics/config/data/inference_config.py
careamics/config/data/ng_data_config.py
careamics/config/data/normalization_config.py
careamics/config/data/tile_information.py
careamics/config/data/patch_filter/__init__.py
careamics/config/data/patch_filter/filter_config.py
careamics/config/data/patch_filter/mask_filter_config.py
careamics/config/data/patch_filter/max_filter_config.py
careamics/config/data/patch_filter/meanstd_filter_config.py
careamics/config/data/patch_filter/shannon_filter_config.py
careamics/config/data/patching_strategies/__init__.py
careamics/config/data/patching_strategies/_overlapping_patched_config.py
careamics/config/data/patching_strategies/_patched_config.py
careamics/config/data/patching_strategies/random_patching_config.py
careamics/config/data/patching_strategies/sequential_patching_config.py
careamics/config/data/patching_strategies/tiled_patching_config.py
careamics-0.0.21.dist-info/METADATA
careamics-0.0.21.dist-info/WHEEL
careamics-0.0.21.dist-info/entry_points.txt
careamics-0.0.21.dist-info/licenses/LICENSE
careamics-0.0.21.dist-info/RECORD
