Metadata-Version: 2.4
Name: careamics
Version: 0.0.21
Summary: Toolbox for running N2V and friends.
Project-URL: homepage, https://careamics.github.io/
Project-URL: repository, https://github.com/CAREamics/careamics
Author-email: CAREamics team <rse@fht.org>, Ashesh <ashesh.ashesh@fht.org>, Federico Carrara <federico.carrara@fht.org>, Melisande Croft <melisande.croft@fht.org>, Joran Deschamps <joran.deschamps@fht.org>, Vera Galinova <vera.galinova@fht.org>, Igor Zubarev <igor.zubarev@fht.org>
License: BSD-3-Clause
License-File: LICENSE
Classifier: Development Status :: 3 - Alpha
Classifier: License :: OSI Approved :: BSD License
Classifier: Programming Language :: Python :: 3
Classifier: Programming Language :: Python :: 3.11
Classifier: Programming Language :: Python :: 3.12
Classifier: Programming Language :: Python :: 3.13
Classifier: Typing :: Typed
Requires-Python: >=3.11
Requires-Dist: bioimageio-core>=0.9.0
Requires-Dist: matplotlib<=3.10.8
Requires-Dist: numpy>=1.21
Requires-Dist: numpy>=2.1.0; python_version >= '3.13'
Requires-Dist: pillow<=12.1.0
Requires-Dist: psutil<=7.2.1
Requires-Dist: pydantic<=2.12.5,>=2.11
Requires-Dist: pytorch-lightning<=2.6.0,>=2.2
Requires-Dist: pyyaml!=6.0.0,<=6.0.3
Requires-Dist: scikit-image<=0.26.0
Requires-Dist: tifffile<=2026.1.14
Requires-Dist: torch<=2.9.1,>=2.0
Requires-Dist: torchmetrics<1.5.0,>=0.11.0
Requires-Dist: torchvision<=0.24.1
Requires-Dist: typer<=0.21.1,>=0.12.3
Requires-Dist: validators<=0.35.0
Requires-Dist: zarr<4.0.0,>=3.0.0
Provides-Extra: czi
Requires-Dist: pylibczirw<6.0.0,>=4.1.2; extra == 'czi'
Provides-Extra: examples
Requires-Dist: careamics-portfolio; extra == 'examples'
Requires-Dist: jupyter; extra == 'examples'
Provides-Extra: tensorboard
Requires-Dist: protobuf==5.29.1; extra == 'tensorboard'
Requires-Dist: tensorboard; extra == 'tensorboard'
Provides-Extra: wandb
Requires-Dist: wandb; extra == 'wandb'
